ai_patch/__init__.py
ai_patch/__main__.py
ai_patch/cli.py
ai_patch/config.py
ai_patch/report.py
ai_patch/telemetry.py
ai_patch/checks/__init__.py
ai_patch/checks/cost.py
ai_patch/checks/retries.py
ai_patch/checks/streaming.py
ai_patch/checks/trace.py
ai_patch_doctor-0.1.4.dist-info/METADATA
ai_patch_doctor-0.1.4.dist-info/WHEEL
ai_patch_doctor-0.1.4.dist-info/entry_points.txt
ai_patch_doctor-0.1.4.dist-info/top_level.txt
ai_patch_doctor-0.1.4.dist-info/RECORD
