Metadata-Version: 2.4
Name: ai-patch-doctor
Version: 0.1.4
Summary: Fix-first incident patcher for AI API issues - diagnose streaming, retries, cost, and traceability problems
Author-email: AI Badgr <support@aibadgr.com>
License-Expression: MIT
Project-URL: Homepage, https://github.com/michaelbrinkworth/ai-patch-doctor
Project-URL: Documentation, https://github.com/michaelbrinkworth/ai-patch-doctor
Project-URL: Repository, https://github.com/michaelbrinkworth/ai-patch-doctor
Project-URL: Issues, https://github.com/michaelbrinkworth/ai-patch-doctor/issues
Keywords: ai,openai,anthropic,gemini,debugging,streaming,api
Classifier: Development Status :: 4 - Beta
Classifier: Intended Audience :: Developers
Classifier: Programming Language :: Python :: 3
Classifier: Programming Language :: Python :: 3.8
Classifier: Programming Language :: Python :: 3.9
Classifier: Programming Language :: Python :: 3.10
Classifier: Programming Language :: Python :: 3.11
Classifier: Programming Language :: Python :: 3.12
Requires-Python: >=3.8
Requires-Dist: requests>=2.31.0
Requires-Dist: click>=8.1.0
Requires-Dist: pyyaml>=6.0
Requires-Dist: httpx>=0.24.0
Requires-Dist: posthog>=3.0.0
Provides-Extra: dev
Requires-Dist: pytest>=7.0; extra == "dev"
Requires-Dist: pytest-cov>=4.0; extra == "dev"
Requires-Dist: black>=23.0; extra == "dev"
Requires-Dist: mypy>=1.0; extra == "dev"
